zoom/__init__.py
zoom/__main__.py
zoom/__version__.py
zoom/alerts.py
zoom/api.py
zoom/apps.py
zoom/audit.py
zoom/auditing.py
zoom/background.py
zoom/browse.py
zoom/buckets.py
zoom/cache.py
zoom/collect.py
zoom/component.py
zoom/config.py
zoom/context.py
zoom/cookies.py
zoom/database.py
zoom/exceptions.py
zoom/fields.py
zoom/fill.py
zoom/forms.py
zoom/helpers.py
zoom/html.py
zoom/impersonation.py
zoom/instances.py
zoom/jsonz.py
zoom/logging.py
zoom/mail.py
zoom/middleware.py
zoom/migrations.py
zoom/models.py
zoom/mvc.py
zoom/packages.py
zoom/page.py
zoom/profiler.py
zoom/queues.py
zoom/records.py
zoom/render.py
zoom/request.py
zoom/response.py
zoom/server.py
zoom/services.py
zoom/session.py
zoom/settings.py
zoom/site.py
zoom/sites.py
zoom/snippets.py
zoom/sqltools.py
zoom/store.py
zoom/templates.py
zoom/tools.py
zoom/users.py
zoom/utils.py
zoom/validators.py
zoom/_assets/boilerplates/apps/basic/app.py
zoom/_assets/boilerplates/apps/basic/config.ini
zoom/_assets/boilerplates/apps/basic/index.py
zoom/_assets/boilerplates/instances/basic/apps/default.ini
zoom/_assets/boilerplates/instances/basic/sites/localhost/.gitinclude
zoom/_assets/boilerplates/instances/basic/themes/.gitinclude
zoom/_assets/boilerplates/sites/basic/site.ini
zoom/_assets/boilerplates/themes/basic/README.md
zoom/_assets/boilerplates/themes/basic/content.html
zoom/_assets/boilerplates/themes/basic/default.html
zoom/_assets/boilerplates/themes/basic/index.html
zoom/_assets/boilerplates/themes/basic/css/buttons.css
zoom/_assets/boilerplates/themes/basic/css/components.css
zoom/_assets/boilerplates/themes/basic/css/containers.css
zoom/_assets/boilerplates/themes/basic/css/content.css
zoom/_assets/boilerplates/themes/basic/css/flags.css
zoom/_assets/boilerplates/themes/basic/css/guide.css
zoom/_assets/boilerplates/themes/basic/css/navigation.css
zoom/_assets/boilerplates/themes/basic/css/pricebox.css
zoom/_assets/boilerplates/themes/basic/css/print.css
zoomfoundry-6.27.0.dist-info/LICENSE
zoomfoundry-6.27.0.dist-info/METADATA
zoomfoundry-6.27.0.dist-info/WHEEL
zoomfoundry-6.27.0.dist-info/entry_points.txt
zoomfoundry-6.27.0.dist-info/top_level.txt
zoomfoundry-6.27.0.dist-info/RECORD
