Metadata-Version: 2.1
Name: zoomfoundry
Version: 6.27.0
Summary: A dynamic Web Framework that promotes modularity and rapid prototyping
Home-page: https://github.com/ZoomFoundry/ZoomFoundry
Author: DSI Labs
Author-email: support@dsilabs.ca
Classifier: Development Status :: 3 - Alpha
Classifier: Environment :: Web Environment
Classifier: Intended Audience :: Developers
Classifier: License :: OSI Approved :: MIT License
Classifier: Operating System :: OS Independent
Classifier: Programming Language :: Python
Classifier: Programming Language :: Python :: 3
Classifier: Programming Language :: Python :: 3.7
Classifier: Programming Language :: Python :: 3.8
Classifier: Programming Language :: Python :: 3.9
Classifier: Programming Language :: Python :: 3.12
Classifier: Programming Language :: Python :: 3 :: Only
Classifier: Topic :: Internet :: WWW/HTTP
Classifier: Topic :: Internet :: WWW/HTTP :: Dynamic Content
Classifier: Topic :: Internet :: WWW/HTTP :: WSGI
Classifier: Topic :: Software Development :: Libraries :: Application Frameworks
Classifier: Topic :: Software Development :: Libraries :: Python Modules
License-File: LICENSE
Requires-Dist: PyMySQL >=0.10.1
Requires-Dist: bcrypt <4.0.1
Requires-Dist: passlib >=1.7.1
Requires-Dist: markdown >=2.6.1
Requires-Dist: Pillow >=1.0
Requires-Dist: faker
Requires-Dist: docopt
Requires-Dist: Werkzeug <=3.0.0
Requires-Dist: croniter
Requires-Dist: pypugjs >=5.9.12
Requires-Dist: libsass >=0.19.4
Requires-Dist: pytz >=2024.1
Requires-Dist: pytzdata >=2020.1
Requires-Dist: requests >=2.25.1
Requires-Dist: Flask ==2.2.5
Requires-Dist: tornado ==6.1
Requires-Dist: livereload >=2.5.1
